daisyfl/__init__.py
daisyfl/client/__init__.py
daisyfl/client/app.py
daisyfl/client/client.py
daisyfl/client/client_operator_manager.py
daisyfl/client/dpfedavg_numpy_client.py
daisyfl/client/grpc_client/__init__.py
daisyfl/client/grpc_client/c2z_connection.py
daisyfl/client/grpc_client/message_handler.py
daisyfl/client/grpc_server/__init__.py
daisyfl/client/grpc_server/client_service_servicer.py
daisyfl/client/grpc_server/grpc_server.py
daisyfl/client/numpy_client.py
daisyfl/client/trainer.py
daisyfl/common/__init__.py
daisyfl/common/dp.py
daisyfl/common/logger.py
daisyfl/common/metadata.py
daisyfl/common/parameter.py
daisyfl/common/serde.py
daisyfl/common/typing.py
daisyfl/master/__init__.py
daisyfl/master/app.py
daisyfl/master/grpc_server/__init__.py
daisyfl/master/grpc_server/grpc_server.py
daisyfl/master/grpc_server/master_service_servicer.py
daisyfl/master/server_api_handler.py
daisyfl/operator/__init__.py
daisyfl/operator/base/__init__.py
daisyfl/operator/base/client_logic.py
daisyfl/operator/base/server_logic.py
daisyfl/operator/base_async/__init__.py
daisyfl/operator/base_async/client_logic.py
daisyfl/operator/base_async/server_logic.py
daisyfl/operator/msg_demo/client_logic.py
daisyfl/operator/msg_demo/msg.py
daisyfl/operator/msg_demo/server_logic.py
daisyfl/operator/msg_demo/zone_server_logic.py
daisyfl/operator/sec_agg/client_logic.py
daisyfl/operator/sec_agg/common.py
daisyfl/operator/sec_agg/primitives.py
daisyfl/operator/sec_agg/server_logic.py
daisyfl/operator/strategy/__init__.py
daisyfl/operator/strategy/aggregate.py
daisyfl/operator/strategy/dpfedavg_adaptive.py
daisyfl/operator/strategy/dpfedavg_fixed.py
daisyfl/operator/strategy/fault_tolerant_fedavg.py
daisyfl/operator/strategy/fedadagrad.py
daisyfl/operator/strategy/fedadam.py
daisyfl/operator/strategy/fedasync.py
daisyfl/operator/strategy/fedavg.py
daisyfl/operator/strategy/fedavg_android.py
daisyfl/operator/strategy/fedavgm.py
daisyfl/operator/strategy/fedopt.py
daisyfl-0.5.3.dist-info/LICENSE
daisyfl-0.5.3.dist-info/WHEEL
daisyfl-0.5.3.dist-info/METADATA
daisyfl-0.5.3.dist-info/RECORD
